Weather_API_MASI/__init__.py
Weather_API_MASI/run_weather_tool.py
weather_api_masi-0.5.dist-info/METADATA
weather_api_masi-0.5.dist-info/WHEEL
weather_api_masi-0.5.dist-info/entry_points.txt
weather_api_masi-0.5.dist-info/top_level.txt
weather_api_masi-0.5.dist-info/RECORD
