Metadata-Version: 2.4
Name: Weather_API_MASI
Version: 0.5
Requires-Dist: requests>=2.31.0
Requires-Dist: selenium>=4.28.1
Requires-Dist: geopy>=2.4.1
Requires-Dist: webdriver_manager>=4.0.2
Requires-Dist: argparse
Requires-Dist: python-dotenv>=0.19.0
Requires-Dist: beautifulsoup4>=0.0.2
Requires-Dist: pandas>=2.2.3
Requires-Dist: seaborn>=0.13.2
Requires-Dist: matplotlib>=3.10.1
Dynamic: description
Dynamic: description-content-type
Dynamic: requires-dist
